pythin/__init__.py
pythin-0.1.0.dist-info/WHEEL
pythin-0.1.0.dist-info/METADATA
pythin-0.1.0.dist-info/RECORD
