Metadata-Version: 2.1
Name: pythin
Version: 0.1.0
Summary: Simpler Python
Author: WhatDoWeDoNow
Requires-Python: >=3.8,<4.0
Classifier: Programming Language :: Python :: 3
Classifier: Programming Language :: Python :: 3.8
Classifier: Programming Language :: Python :: 3.9
